LICENSE
README.md
setup.py
core/__init__.py
core/explorers/__init__.py
core/explorers/beam_search.py
core/explorers/graph_explorer.py
core/explorers/simmulated_annealing.py
core/rankers/__init__.py
core/rankers/brute_force.py
core/rankers/external_model.py
core/rankers/lookup_table.py
core/rankers/random.py
core/rankers/ranking_algorithm.py
transformers/__init__.py
transformers/subtransformer.py
transformers/transformer.py
transformers/basic/__init__.py
transformers/basic/category_transformer.py
transformers/basic/number_transformer.py
transformers/basic/string_transformer.py
transformers/basic/subtransformers/__init__.py
transformers/basic/subtransformers/category_modifier.py
transformers/basic/subtransformers/delete.py
transformers/basic/subtransformers/increment.py
transformers/basic/subtransformers/insert.py
transformers/basic/subtransformers/substitution.py
transformers/binary/__init__.py
transformers/binary/binary_transformer.py
transformers/binary/subtransformers/__init__.py
transformers/binary/subtransformers/binary_to_bytez.py
transformers/binary/subtransformers/imports_append.py
transformers/binary/subtransformers/overlay_append.py
transformers/binary/subtransformers/remove_debug.py
transformers/binary/subtransformers/section_add.py
transformers/binary/subtransformers/section_rename.py
transformers/binary/subtransformers/upx_pack.py
transformers/binary/subtransformers/upx_unpack.py
uret/__init__.py
uret.egg-info/PKG-INFO
uret.egg-info/SOURCES.txt
uret.egg-info/dependency_links.txt
uret.egg-info/requires.txt
uret.egg-info/top_level.txt
uret/core/__init__.py
uret/core/explorers/__init__.py
uret/core/explorers/beam_search.py
uret/core/explorers/graph_explorer.py
uret/core/explorers/simmulated_annealing.py
uret/core/rankers/__init__.py
uret/core/rankers/brute_force.py
uret/core/rankers/external_model.py
uret/core/rankers/lookup_table.py
uret/core/rankers/random.py
uret/core/rankers/ranking_algorithm.py
uret/transformers/__init__.py
uret/transformers/subtransformer.py
uret/transformers/transformer.py
uret/transformers/basic/__init__.py
uret/transformers/basic/category_transformer.py
