Metadata-Version: 2.1
Name: uret
Version: 0.1
Summary: Toolkit for generic adversarial machine learning evaluationsI.
Home-page: https://github.com/IBM/URET
Author: Kevin Eykholt
Author-email: kheykholt@ibm.com
Maintainer: Kevin Eykholt
Maintainer-email: kheykholt@ibm.com
License: MIT
Provides-Extra: all
Provides-Extra: binary
Provides-Extra: rl
Provides-Extra: non-framework
License-File: LICENSE
